pyCGM2/__init__.py
pyCGM2/enums.py
pyCGM2/generatePipeline.py
pyCGM2/log.py
pyCGM2/Anomaly/__init__.py
pyCGM2/Anomaly/anomalyCorrectionProcedures.py
pyCGM2/Anomaly/anomalyDetectionProcedures.py
pyCGM2/Anomaly/anomalyFilters.py
pyCGM2/Apps/__init__.py
pyCGM2/Apps/Commands/__init__.py
pyCGM2/Apps/Commands/commands.py
pyCGM2/Apps/QtmApps/__init__.py
pyCGM2/Apps/QtmApps/CGMi/CGM11_workflow.py
pyCGM2/Apps/QtmApps/CGMi/CGM1_workflow.py
pyCGM2/Apps/QtmApps/CGMi/CGM21_workflow.py
pyCGM2/Apps/QtmApps/CGMi/CGM22_workflow.py
pyCGM2/Apps/QtmApps/CGMi/CGM23_workflow.py
pyCGM2/Apps/QtmApps/CGMi/CGM24_workflow.py
pyCGM2/Apps/QtmApps/CGMi/CGM25_workflow.py
pyCGM2/Apps/QtmApps/CGMi/CGM26_workflow.py
pyCGM2/Apps/QtmApps/CGMi/__init__.py
pyCGM2/Apps/ViconApps/CgmArgsManager.py
pyCGM2/Apps/ViconApps/__init__.py
pyCGM2/Apps/ViconApps/CGM1/CGM1_Calibration.py
pyCGM2/Apps/ViconApps/CGM1/CGM1_Fitting.py
pyCGM2/Apps/ViconApps/CGM1/__init__.py
pyCGM2/Apps/ViconApps/CGM1_1/CGM1_1_Calibration.py
pyCGM2/Apps/ViconApps/CGM1_1/CGM1_1_Fitting.py
pyCGM2/Apps/ViconApps/CGM1_1/__init__.py
pyCGM2/Apps/ViconApps/CGM2_1/CGM2_1_Calibration.py
pyCGM2/Apps/ViconApps/CGM2_1/CGM2_1_Fitting.py
pyCGM2/Apps/ViconApps/CGM2_1/__init__.py
pyCGM2/Apps/ViconApps/CGM2_2/CGM2_2_Calibration.py
pyCGM2/Apps/ViconApps/CGM2_2/CGM2_2_Fitting.py
pyCGM2/Apps/ViconApps/CGM2_2/__init__.py
pyCGM2/Apps/ViconApps/CGM2_3/CGM2_3_Calibration.py
pyCGM2/Apps/ViconApps/CGM2_3/CGM2_3_Fitting.py
pyCGM2/Apps/ViconApps/CGM2_3/__init__.py
pyCGM2/Apps/ViconApps/CGM2_4/CGM2_4_Calibration.py
pyCGM2/Apps/ViconApps/CGM2_4/CGM2_4_Fitting.py
pyCGM2/Apps/ViconApps/CGM2_4/__init__.py
pyCGM2/Apps/ViconApps/CGM2_5/CGM2_5_Calibration.py
pyCGM2/Apps/ViconApps/CGM2_5/CGM2_5_Fitting.py
pyCGM2/Apps/ViconApps/CGM2_5/__init__.py
pyCGM2/Apps/ViconApps/CGM2_6/CGM_Knee2DofCalibration.py
pyCGM2/Apps/ViconApps/CGM2_6/CGM_KneeSARA.py
pyCGM2/Apps/ViconApps/CGM2_6/__init__.py
pyCGM2/Apps/ViconApps/Events/__init__.py
pyCGM2/Apps/ViconApps/Events/zeniDetector.py
pyCGM2-4.3.dist-info/METADATA
pyCGM2-4.3.dist-info/WHEEL
pyCGM2-4.3.dist-info/entry_points.txt
pyCGM2-4.3.dist-info/licence
pyCGM2-4.3.dist-info/top_level.txt
pyCGM2-4.3.dist-info/RECORD
